odoo/addons/pos_partner_lang/README.rst
odoo/addons/pos_partner_lang/__init__.py
odoo/addons/pos_partner_lang/__manifest__.py
odoo/addons/pos_partner_lang/i18n/pos_partner_lang.pot
odoo/addons/pos_partner_lang/models/__init__.py
odoo/addons/pos_partner_lang/models/res_partner.py
odoo/addons/pos_partner_lang/readme/CONTRIBUTORS.rst
odoo/addons/pos_partner_lang/readme/DESCRIPTION.rst
odoo/addons/pos_partner_lang/static/description/icon.png
odoo/addons/pos_partner_lang/static/description/index.html
odoo/addons/pos_partner_lang/static/description/pos_partner_lang.png
odoo/addons/pos_partner_lang/static/src/js/models.js
odoo/addons/pos_partner_lang/static/src/xml/screens.xml
odoo/addons/pos_partner_lang/tests/__init__.py
odoo/addons/pos_partner_lang/tests/test_pos_partner_lang.py
odoo/addons/pos_partner_lang/views/assets.xml
odoo13_addon_pos_partner_lang-13.0.1.0.1.dist-info/METADATA
odoo13_addon_pos_partner_lang-13.0.1.0.1.dist-info/WHEEL
odoo13_addon_pos_partner_lang-13.0.1.0.1.dist-info/top_level.txt
odoo13_addon_pos_partner_lang-13.0.1.0.1.dist-info/RECORD
